etl/__init__.py
etl/cmdline.py
etl/exceptions.py
etl/log.py
etl/manage.py
etl/config/__init__.py
etl/config/settings.yml
etl/dest/__init__.py
etl/dest/base.py
etl/dest/file.py
etl/process/__init__.py
etl/process/base.py
etl/process/strip.py
etl/source/__init__.py
etl/source/base.py
etl/source/file.py
example_etl/__init__.py
example_etl/cmdline.py
example_etl/exceptions.py
example_etl/log.py
example_etl/manage.py
example_etl/config/__init__.py
example_etl/config/settings.yml
example_etl/dest/__init__.py
example_etl/dest/base.py
example_etl/dest/file.py
example_etl/process/__init__.py
example_etl/process/base.py
example_etl/process/strip.py
example_etl/source/__init__.py
example_etl/source/base.py
example_etl/source/file.py
example_etl-0.0.1.dev0.data/data/etc/example_etl/settings.yml
example_etl-0.0.1.dev0.dist-info/LICENSE
example_etl-0.0.1.dev0.dist-info/METADATA
example_etl-0.0.1.dev0.dist-info/WHEEL
example_etl-0.0.1.dev0.dist-info/entry_points.txt
example_etl-0.0.1.dev0.dist-info/top_level.txt
example_etl-0.0.1.dev0.dist-info/RECORD
