Metadata-Version: 2.1
Name: example-etl
Version: 0.0.1.dev0
Summary: Etl tools
Home-page: UNKNOWN
Author: huagang
Author-email: huagang517@126.com
License: UNKNOWN
Keywords: etl
Platform: UNKNOWN
Classifier: Operating System :: OS Independent
Classifier: Programming Language :: Python :: 3.10
License-File: LICENSE
Requires-Dist: click (==8.0.3)
Requires-Dist: dynaconf (==3.1.7)
Requires-Dist: stevedore (==3.5.0)
